lesivka/__init__.py
lesivka/__main__.py
lesivka/version.py
lesivka-99.0.dist-info/LICENSE
lesivka-99.0.dist-info/METADATA
lesivka-99.0.dist-info/WHEEL
lesivka-99.0.dist-info/top_level.txt
lesivka-99.0.dist-info/RECORD
