Metadata-Version: 2.1
Name: lesivka
Version: 99.0
Summary: Python library to convert to/from Lesivka
Home-page: UNKNOWN
Author: Oleksandr Tishyn
Author-email: 1079805+Mystic-Mirage@users.noreply.github.com
License: CC0 1.0 Universal
Project-URL: Source Code, https://github.com/lesiwka/python-lesivka
Platform: UNKNOWN
Classifier: Programming Language :: Python :: 3
Classifier: Programming Language :: Python :: 3.6
Classifier: Programming Language :: Python :: 3.7
Classifier: Programming Language :: Python :: 3.8
Classifier: Programming Language :: Python :: 3.9
Classifier: Programming Language :: Python :: 3.10
License-File: LICENSE
Requires-Dist: lesiwka
Provides-Extra: test
Requires-Dist: pytest ; extra == 'test'
